findig/content.py
findig/context.py
findig/data_model.py
findig/dispatcher.py
findig/json.py
findig/resource.py
findig/utils.py
findig/VERSION
findig/wrappers.py
findig/__init__.py
findig/extras/redis.py
findig/extras/sql.py
findig/extras/__init__.py
findig/tools/counter.py
findig/tools/dataset.py
findig/tools/validator.py
findig/tools/__init__.py
findig/tools/protector/scopeutil.py
findig/tools/protector/__init__.py
Findig-0.1.0.dist-info/DESCRIPTION.rst
Findig-0.1.0.dist-info/METADATA
Findig-0.1.0.dist-info/metadata.json
Findig-0.1.0.dist-info/RECORD
Findig-0.1.0.dist-info/top_level.txt
Findig-0.1.0.dist-info/WHEEL
