Metadata-Version: 2.0
Name: Findig
Version: 0.1.0
Summary: A micro-framework for RESTful web applications.
Home-page: https://github.com/geniphi/findig
Author: Te-je Rodgers
Author-email: tjd.rodgers@gmail.com
License: MIT
Requires-Dist: werkzeug
Provides-Extra: sql
Requires-Dist: sqlalchemy; extra == 'sql'
Provides-Extra: redis
Requires-Dist: redis; extra == 'redis'
